{"alias":"@cdalton713/eslint","config":{"schema":"https://moonrepo.dev/schemas/project.json","dependsOn":[],"docker":{"file":{"buildTask":null,"image":null,"startTask":null},"scaffold":{"include":[]}},"env":{},"fileGroups":{},"id":null,"language":"unknown","owners":{"customGroups":{},"defaultOwner":null,"optional":false,"paths":[],"requiredApprovals":0},"platform":null,"project":null,"stack":"unknown","tags":[],"tasks":{},"toolchain":{"bun":null,"deno":null,"node":null,"rust":null,"typescript":null},"type":"library","workspace":{"inheritedTasks":{"exclude":[],"include":null,"rename":{}}}},"dependencies":[],"fileGroups":{"configs":{"env":[],"files":[],"globs":["packages/eslint/**/*.{md,mdx,yml,yaml,json}"],"id":"configs"},"inputs":{"env":[],"files":["packages/eslint/tsconfig.json","tsconfig.options.json"],"globs":["packages/eslint/src/**/*","packages/eslint/__tests__/**/*","packages/eslint/tsconfig.*.json"],"id":"inputs"},"markdown":{"env":[],"files":[],"globs":["packages/eslint/**/*.{md,mdx}"],"id":"markdown"},"outputs":{"env":[],"files":[],"globs":["packages/eslint/dist/**/*","packages/eslint/lib/**/*"],"id":"outputs"},"sst":{"env":[],"files":[],"globs":[".sst/**/*",".build/**/*"],"id":"sst"},"sst-build":{"env":[],"files":[],"globs":["packages/eslint/src/**/*","ig-sst/**/*"],"id":"sst-build"},"types":{"env":[],"files":[],"globs":["packages/eslint/types/**/*"],"id":"types"}},"id":"eslint","inherited":{"order":["*","node","typescript","node-library","typescript-library"],"config":{"schema":"https://moonrepo.dev/schemas/tasks.json","extends":null,"fileGroups":{"sst-build":["src/**/*","/ig-sst/**/*"],"inputs":["src/**/*","__tests__/**/*","tsconfig.json","tsconfig.*.json","/tsconfig.options.json"],"outputs":["dist/**/*","lib/**/*"],"configs":["**/*.{md,mdx,yml,yaml,json}"],"markdown":["**/*.{md,mdx}"],"types":["types/**/*"],"sst":["/.sst/**/*","/.build/**/*"]},"implicitDeps":["^:build"],"implicitInputs":["package.json"],"tasks":{"build":{"extends":null,"description":null,"command":"packemon","args":["build","--addEngines","--addExports","--declaration"],"deps":[],"env":{"NODE_ENV":"production"},"globalInputs":["/.moon/tasks/node-library.yml"],"inputs":["@group(inputs)"],"local":null,"outputs":["lib"],"options":{"affectedFiles":null,"affectedPassInputs":null,"allowFailure":null,"cache":null,"envFile":null,"internal":null,"interactive":null,"mergeArgs":null,"mergeDeps":null,"mergeEnv":null,"mergeInputs":null,"mergeOutputs":null,"mutex":null,"outputStyle":null,"persistent":null,"retryCount":null,"runDepsInParallel":null,"runInCI":null,"runFromWorkspaceRoot":null,"shell":null,"timeout":null,"unixShell":null,"windowsShell":null},"platform":"node","script":null,"type":null},"lint":{"extends":null,"description":null,"command":"noop","args":null,"deps":["~:build"],"env":{},"globalInputs":["/.moon/tasks/node.yml"],"inputs":["@group(inputs)","@group(types)"],"local":null,"outputs":null,"options":{"affectedFiles":null,"affectedPassInputs":null,"allowFailure":null,"cache":null,"envFile":null,"internal":null,"interactive":null,"mergeArgs":null,"mergeDeps":null,"mergeEnv":null,"mergeInputs":null,"mergeOutputs":null,"mutex":null,"outputStyle":null,"persistent":null,"retryCount":null,"runDepsInParallel":false,"runInCI":null,"runFromWorkspaceRoot":null,"shell":null,"timeout":null,"unixShell":null,"windowsShell":null},"platform":"node","script":null,"type":null},"lint_eslint":{"extends":null,"description":null,"command":["eslint","--ext",".js,.jsx,.ts,.tsx","--fix","--report-unused-disable-directives","--no-error-on-unmatched-pattern","--exit-on-fatal-error","--ignore-path","@in(0)","--cache","."],"args":null,"deps":[],"env":{},"globalInputs":["/.moon/tasks/node.yml"],"inputs":["/.eslintignore","@globs(inputs)","@group(types)","*.config.*","**/.eslintrc.*","/.eslintrc.*","/tsconfig.options.json"],"local":null,"outputs":null,"options":{"affectedFiles":null,"affectedPassInputs":null,"allowFailure":null,"cache":null,"envFile":null,"internal":null,"interactive":null,"mergeArgs":null,"mergeDeps":null,"mergeEnv":null,"mergeInputs":null,"mergeOutputs":null,"mutex":null,"outputStyle":null,"persistent":null,"retryCount":null,"runDepsInParallel":null,"runInCI":null,"runFromWorkspaceRoot":null,"shell":null,"timeout":null,"unixShell":null,"windowsShell":null},"platform":"node","script":null,"type":null},"lint_prettier":{"extends":null,"description":null,"command":["prettier","--config","@in(4)","--ignore-path","@in(0)","--write","."],"args":null,"deps":[],"env":{},"globalInputs":["/.moon/tasks/node.yml"],"inputs":["/.prettierignore","@group(inputs)","@globs(configs)","@globs(markdown)","/.prettierrc.json"],"local":null,"outputs":null,"options":{"affectedFiles":null,"affectedPassInputs":null,"allowFailure":null,"cache":null,"envFile":null,"internal":null,"interactive":null,"mergeArgs":null,"mergeDeps":null,"mergeEnv":null,"mergeInputs":null,"mergeOutputs":null,"mutex":null,"outputStyle":"buffer-only-failure","persistent":null,"retryCount":3,"runDepsInParallel":null,"runInCI":null,"runFromWorkspaceRoot":null,"shell":null,"timeout":null,"unixShell":null,"windowsShell":null},"platform":"node","script":null,"type":null},"lint_tsc":{"extends":null,"description":null,"command":["tsc","--build","--pretty"],"args":null,"deps":[],"env":{},"globalInputs":["/.moon/tasks/node.yml"],"inputs":["@group(inputs)","@group(types)"],"local":null,"outputs":null,"options":{"affectedFiles":null,"affectedPassInputs":null,"allowFailure":null,"cache":null,"envFile":null,"internal":null,"interactive":null,"mergeArgs":null,"mergeDeps":null,"mergeEnv":null,"mergeInputs":null,"mergeOutputs":null,"mutex":null,"outputStyle":null,"persistent":null,"retryCount":null,"runDepsInParallel":null,"runInCI":null,"runFromWorkspaceRoot":null,"shell":null,"timeout":null,"unixShell":null,"windowsShell":null},"platform":"node","script":null,"type":null}},"taskOptions":null},"layers":{".moon/tasks/node.yml":{"$schema":"https://moonrepo.dev/schemas/tasks.json","fileGroups":{"sst-build":["src/**/*","/ig-sst/**/*"],"inputs":["src/**/*","__tests__/**/*","tsconfig.json","tsconfig.*.json","/tsconfig.options.json"],"outputs":["dist/**/*","lib/**/*"],"configs":["**/*.{md,mdx,yml,yaml,json}"],"markdown":["**/*.{md,mdx}"],"types":["types/**/*"],"sst":["/.sst/**/*","/.build/**/*"]},"implicitDeps":["^:build"],"implicitInputs":["package.json"],"tasks":{"lint":{"command":"noop","deps":["~:build"],"inputs":["@group(inputs)","@group(types)"],"options":{"runDepsInParallel":false},"platform":"node"},"lint_eslint":{"command":["eslint","--ext",".js,.jsx,.ts,.tsx","--fix","--report-unused-disable-directives","--no-error-on-unmatched-pattern","--exit-on-fatal-error","--ignore-path","@in(0)","--cache","."],"inputs":["/.eslintignore","@globs(inputs)","@group(types)","*.config.*","**/.eslintrc.*","/.eslintrc.*","/tsconfig.options.json"],"platform":"node"},"lint_prettier":{"command":["prettier","--config","@in(4)","--ignore-path","@in(0)","--write","."],"inputs":["/.prettierignore","@group(inputs)","@globs(configs)","@globs(markdown)","/.prettierrc.json"],"options":{"outputStyle":"buffer-only-failure","retryCount":3},"platform":"node"},"lint_tsc":{"command":["tsc","--build","--pretty"],"inputs":["@group(inputs)","@group(types)"],"platform":"node"}}},".moon/tasks/node-library.yml":{"$schema":"https://moonrepo.dev/schemas/tasks.json","tasks":{"build":{"command":"packemon","args":["build","--addEngines","--addExports","--declaration"],"env":{"NODE_ENV":"production"},"inputs":["@group(inputs)"],"outputs":["lib"],"platform":"node"}}}},"taskLayers":{"build":[".moon/tasks/node-library.yml"],"lint":[".moon/tasks/node.yml"],"lint_prettier":[".moon/tasks/node.yml"],"lint_eslint":[".moon/tasks/node.yml"],"lint_tsc":[".moon/tasks/node.yml"]}},"language":"typescript","platform":"node","stack":"unknown","root":"/Users/christian/Projects/dev/packages/eslint","source":"packages/eslint","tasks":{"build":{"args":["build","--addEngines","--addExports","--declaration"],"command":"packemon","deps":[],"description":null,"env":{"NODE_ENV":"production"},"id":"build","inputs":["@group(inputs)","package.json","/.moon/*.yml","/.moon/tasks/node-library.yml"],"inputEnv":[],"inputFiles":["packages/eslint/tsconfig.json","tsconfig.options.json","packages/eslint/package.json",".moon/tasks/node-library.yml"],"inputGlobs":["packages/eslint/__tests__/**/*","packages/eslint/tsconfig.*.json","packages/eslint/src/**/*",".moon/*.yml"],"metadata":{"emptyInputs":false,"expanded":true,"localOnly":false,"rootLevel":false},"options":{"affectedFiles":null,"affectedPassInputs":false,"allowFailure":false,"cache":true,"envFiles":null,"internal":false,"interactive":false,"mergeArgs":"append","mergeDeps":"append","mergeEnv":"append","mergeInputs":"append","mergeOutputs":"append","mutex":null,"outputStyle":null,"persistent":false,"retryCount":0,"runDepsInParallel":true,"runInCI":true,"runFromWorkspaceRoot":false,"shell":null,"timeout":null,"unixShell":null,"windowsShell":null},"outputs":["lib"],"outputFiles":["packages/eslint/lib"],"outputGlobs":[],"platform":"node","script":null,"target":"eslint:build","type":"build"},"lint":{"args":[],"command":"noop","deps":[{"args":null,"env":{},"target":"eslint:build","optional":null}],"description":null,"env":{},"id":"lint","inputs":["@group(inputs)","@group(types)","package.json","/.moon/*.yml","/.moon/tasks/node.yml"],"inputEnv":[],"inputFiles":["packages/eslint/tsconfig.json","tsconfig.options.json","packages/eslint/package.json",".moon/tasks/node.yml"],"inputGlobs":["packages/eslint/__tests__/**/*","packages/eslint/tsconfig.*.json","packages/eslint/types/**/*","packages/eslint/src/**/*",".moon/*.yml"],"metadata":{"emptyInputs":false,"expanded":true,"localOnly":false,"rootLevel":false},"options":{"affectedFiles":null,"affectedPassInputs":false,"allowFailure":false,"cache":true,"envFiles":null,"internal":false,"interactive":false,"mergeArgs":"append","mergeDeps":"append","mergeEnv":"append","mergeInputs":"append","mergeOutputs":"append","mutex":null,"outputStyle":null,"persistent":false,"retryCount":0,"runDepsInParallel":false,"runInCI":true,"runFromWorkspaceRoot":false,"shell":null,"timeout":null,"unixShell":null,"windowsShell":null},"outputs":[],"outputFiles":[],"outputGlobs":[],"platform":"node","script":null,"target":"eslint:lint","type":"test"},"lint_eslint":{"args":["--ext",".js,.jsx,.ts,.tsx","--fix","--report-unused-disable-directives","--no-error-on-unmatched-pattern","--exit-on-fatal-error","--ignore-path","../../.eslintignore","--cache","."],"command":"eslint","deps":[],"description":null,"env":{},"id":"lint_eslint","inputs":["/.eslintignore","@globs(inputs)","@group(types)","*.config.*","**/.eslintrc.*","/.eslintrc.*","/tsconfig.options.json","package.json","/.moon/*.yml","/.moon/tasks/node.yml"],"inputEnv":[],"inputFiles":[".eslintignore","tsconfig.options.json","packages/eslint/package.json",".moon/tasks/node.yml"],"inputGlobs":["packages/eslint/tsconfig.*.json",".eslintrc.*","packages/eslint/types/**/*","packages/eslint/*.config.*",".moon/*.yml","packages/eslint/__tests__/**/*","packages/eslint/**/.eslintrc.*","packages/eslint/src/**/*"],"metadata":{"emptyInputs":false,"expanded":true,"localOnly":false,"rootLevel":false},"options":{"affectedFiles":null,"affectedPassInputs":false,"allowFailure":false,"cache":true,"envFiles":null,"internal":false,"interactive":false,"mergeArgs":"append","mergeDeps":"append","mergeEnv":"append","mergeInputs":"append","mergeOutputs":"append","mutex":null,"outputStyle":null,"persistent":false,"retryCount":0,"runDepsInParallel":true,"runInCI":true,"runFromWorkspaceRoot":false,"shell":null,"timeout":null,"unixShell":null,"windowsShell":null},"outputs":[],"outputFiles":[],"outputGlobs":[],"platform":"node","script":null,"target":"eslint:lint_eslint","type":"test"},"lint_prettier":{"args":["--config","../../.prettierrc.json","--ignore-path","../../.prettierignore","--write","."],"command":"prettier","deps":[],"description":null,"env":{},"id":"lint_prettier","inputs":["/.prettierignore","@group(inputs)","@globs(configs)","@globs(markdown)","/.prettierrc.json","package.json","/.moon/*.yml","/.moon/tasks/node.yml"],"inputEnv":[],"inputFiles":["packages/eslint/tsconfig.json","tsconfig.options.json","packages/eslint/package.json",".prettierignore",".prettierrc.json",".moon/tasks/node.yml"],"inputGlobs":["packages/eslint/__tests__/**/*","packages/eslint/tsconfig.*.json","packages/eslint/**/*.{md,mdx}","packages/eslint/**/*.{md,mdx,yml,yaml,json}","packages/eslint/src/**/*",".moon/*.yml"],"metadata":{"emptyInputs":false,"expanded":true,"localOnly":false,"rootLevel":false},"options":{"affectedFiles":null,"affectedPassInputs":false,"allowFailure":false,"cache":true,"envFiles":null,"internal":false,"interactive":false,"mergeArgs":"append","mergeDeps":"append","mergeEnv":"append","mergeInputs":"append","mergeOutputs":"append","mutex":null,"outputStyle":"buffer-only-failure","persistent":false,"retryCount":3,"runDepsInParallel":true,"runInCI":true,"runFromWorkspaceRoot":false,"shell":null,"timeout":null,"unixShell":null,"windowsShell":null},"outputs":[],"outputFiles":[],"outputGlobs":[],"platform":"node","script":null,"target":"eslint:lint_prettier","type":"test"},"lint_tsc":{"args":["--build","--pretty"],"command":"tsc","deps":[],"description":null,"env":{},"id":"lint_tsc","inputs":["@group(inputs)","@group(types)","package.json","/.moon/*.yml","/.moon/tasks/node.yml"],"inputEnv":[],"inputFiles":["packages/eslint/tsconfig.json","tsconfig.options.json","packages/eslint/package.json",".moon/tasks/node.yml"],"inputGlobs":["packages/eslint/__tests__/**/*","packages/eslint/tsconfig.*.json","packages/eslint/types/**/*","packages/eslint/src/**/*",".moon/*.yml"],"metadata":{"emptyInputs":false,"expanded":true,"localOnly":false,"rootLevel":false},"options":{"affectedFiles":null,"affectedPassInputs":false,"allowFailure":false,"cache":true,"envFiles":null,"internal":false,"interactive":false,"mergeArgs":"append","mergeDeps":"append","mergeEnv":"append","mergeInputs":"append","mergeOutputs":"append","mutex":null,"outputStyle":null,"persistent":false,"retryCount":0,"runDepsInParallel":true,"runInCI":true,"runFromWorkspaceRoot":false,"shell":null,"timeout":null,"unixShell":null,"windowsShell":null},"outputs":[],"outputFiles":[],"outputGlobs":[],"platform":"node","script":null,"target":"eslint:lint_tsc","type":"test"}},"type":"library"}